opentelemetry/gcp_credential_provider/__init__.py
opentelemetry/gcp_credential_provider/version.py
opentelemetry_exporter_credential_provider_gcp-0.60b1.dist-info/METADATA
opentelemetry_exporter_credential_provider_gcp-0.60b1.dist-info/WHEEL
opentelemetry_exporter_credential_provider_gcp-0.60b1.dist-info/entry_points.txt
opentelemetry_exporter_credential_provider_gcp-0.60b1.dist-info/licenses/LICENSE
opentelemetry_exporter_credential_provider_gcp-0.60b1.dist-info/RECORD
